ima_predeployed/__init__.py
ima_predeployed/addresses.py
ima_predeployed/contract_generator.py
ima_predeployed/generator.py
ima_predeployed/upgradeable_contract_generator.py
ima_predeployed/artifacts/.gitkeep
ima_predeployed/artifacts/CommunityLocker.json
ima_predeployed/artifacts/CommunityLocker.meta.json
ima_predeployed/artifacts/ERC1155OnChain.json
ima_predeployed/artifacts/ERC1155OnChain.meta.json
ima_predeployed/artifacts/ERC20OnChain.json
ima_predeployed/artifacts/ERC20OnChain.meta.json
ima_predeployed/artifacts/ERC721OnChain.json
ima_predeployed/artifacts/ERC721OnChain.meta.json
ima_predeployed/artifacts/EthErc20.json
ima_predeployed/artifacts/EthErc20.meta.json
ima_predeployed/artifacts/KeyStorage.json
ima_predeployed/artifacts/KeyStorage.meta.json
ima_predeployed/artifacts/MessageProxyForSchain.json
ima_predeployed/artifacts/MessageProxyForSchain.meta.json
ima_predeployed/artifacts/TokenManager.json
ima_predeployed/artifacts/TokenManager.meta.json
ima_predeployed/artifacts/TokenManagerERC1155.json
ima_predeployed/artifacts/TokenManagerERC1155.meta.json
ima_predeployed/artifacts/TokenManagerERC20.json
ima_predeployed/artifacts/TokenManagerERC20.meta.json
ima_predeployed/artifacts/TokenManagerERC721.json
ima_predeployed/artifacts/TokenManagerERC721.meta.json
ima_predeployed/artifacts/TokenManagerERC721WithMetadata.json
ima_predeployed/artifacts/TokenManagerERC721WithMetadata.meta.json
ima_predeployed/artifacts/TokenManagerEth.json
ima_predeployed/artifacts/TokenManagerEth.meta.json
ima_predeployed/artifacts/TokenManagerLinker.json
ima_predeployed/artifacts/TokenManagerLinker.meta.json
ima_predeployed/contracts/__init__.py
ima_predeployed/contracts/admin_upgradeability_proxy.py
ima_predeployed/contracts/community_locker.py
ima_predeployed/contracts/erc1155_on_chain.py
ima_predeployed/contracts/erc20_on_chain.py
ima_predeployed/contracts/erc721_on_chain.py
ima_predeployed/contracts/eth_erc20.py
ima_predeployed/contracts/key_storage.py
ima_predeployed-2.2.0.dist-info/LICENSE
ima_predeployed-2.2.0.dist-info/METADATA
ima_predeployed-2.2.0.dist-info/WHEEL
ima_predeployed-2.2.0.dist-info/top_level.txt
ima_predeployed-2.2.0.dist-info/RECORD
