Metadata-Version: 2.1
Name: ima-predeployed
Version: 2.2.0
Summary: A tool to generate config for predeployed IMA
Home-page: https://github.com/skalenetwork/IMA
Author: Dmytro Stebaiev
Author-email: dmytro@skalelabs.com
Classifier: Programming Language :: Python :: 3
Classifier: License :: OSI Approved :: GNU Affero General Public License v3
Classifier: Operating System :: OS Independent
Requires-Python: >=3.6
License-File: LICENSE
Requires-Dist: predeployed-generator>=1.2.0
